./AGENTS.md
./PKG-INFO
./README.zh.md
./RELEASE.md
./publish.sh
./uv.lock
./.github/workflows/publish.yml
./.github/workflows/test.yml
./fastapi_toolbox/__init__.py
./fastapi_toolbox/config.py
./fastapi_toolbox/database.py
./fastapi_toolbox/logging.py
./fastapi_toolbox/middleware.py
./fastapi_toolbox/server.py
./fastapi_toolbox/settings.py
./fastapi_toolbox/static_files.py
./tests/__init__.py
./tests/conftest.py
./tests/test_database.py
./tests/test_init.py
./tests/test_settings.py
fastapi_toolbox-0.6.9.dist-info/METADATA
fastapi_toolbox-0.6.9.dist-info/WHEEL
fastapi_toolbox-0.6.9.dist-info/RECORD
