Metadata-Version: 2.4
Name: fastapi-toolbox
Version: 0.6.9
Summary: Common utilities for FastAPI applications
Project-URL: Homepage, https://github.com/wynemo/fastapi-utils
Project-URL: Repository, https://github.com/wynemo/fastapi-utils.git
Project-URL: Issues, https://github.com/wynemo/fastapi-utils/issues
Author-email: wynemo <ggdabin@gmail.com>
License: MIT
Keywords: fastapi,starlette,utilities,web
Classifier: Development Status :: 3 - Alpha
Classifier: Framework :: FastAPI
Classifier: Intended Audience :: Developers
Classifier: License :: OSI Approved :: MIT License
Classifier: Programming Language :: Python :: 3 :: Only
Classifier: Programming Language :: Python :: 3.9
Classifier: Programming Language :: Python :: 3.10
Classifier: Programming Language :: Python :: 3.11
Classifier: Programming Language :: Python :: 3.12
Classifier: Programming Language :: Python :: 3.13
Classifier: Programming Language :: Python :: 3.14
Requires-Python: >=3.9
Requires-Dist: fastapi
Requires-Dist: loguru
Requires-Dist: pydantic-settings
Requires-Dist: sqlmodel
Requires-Dist: starlette
Requires-Dist: uvicorn
Provides-Extra: test
Requires-Dist: pytest>=7.0.0; extra == 'test'
